sapiopylib/__init__.py
sapiopylib/sapio_input_config.py
sapiopylib/sapio_input_data.py
sapiopylib/sapio_native_tools.py
sapiopylib/csp/__init__.py
sapiopylib/csp/data/PyCspFieldMap.py
sapiopylib/csp/data/__init__.py
sapiopylib/csp/data/plotly/PlotlyCspData.py
sapiopylib/csp/data/plotly/PlotlyCspEnums.py
sapiopylib/csp/data/plotly/SapioPyPlotly.py
sapiopylib/csp/data/plotly/__init__.py
sapiopylib/jarvis/JarvisDashboardWebhookContext.py
sapiopylib/jarvis/QQPlotComputer.py
sapiopylib/rest/AccessionService.py
sapiopylib/rest/ClientCallbackService.py
sapiopylib/rest/CustomReportService.py
sapiopylib/rest/DashboardManager.py
sapiopylib/rest/DataMgmtService.py
sapiopylib/rest/DataRecordManagerService.py
sapiopylib/rest/DataService.py
sapiopylib/rest/DataTypeService.py
sapiopylib/rest/ELNService.py
sapiopylib/rest/GroupManagerService.py
sapiopylib/rest/MessengerService.py
sapiopylib/rest/PicklistService.py
sapiopylib/rest/ReportManager.py
sapiopylib/rest/SesssionManagerService.py
sapiopylib/rest/User.py
sapiopylib/rest/UserManagerService.py
sapiopylib/rest/WebhookService.py
sapiopylib/rest/__init__.py
sapiopylib/rest/pojo/CustomReport.py
sapiopylib/rest/pojo/DataRecord.py
sapiopylib/rest/pojo/DataRecordBatchUpdate.py
sapiopylib/rest/pojo/DataRecordPaging.py
sapiopylib/rest/pojo/DataRecordSideLinkPaging.py
sapiopylib/rest/pojo/DateRange.py
sapiopylib/rest/pojo/Message.py
sapiopylib/rest/pojo/Picklist.py
sapiopylib/rest/pojo/Sort.py
sapiopylib/rest/pojo/TableColumn.py
sapiopylib/rest/pojo/UserInfo.py
sapiopylib/rest/pojo/__init__.py
sapiopylib/rest/pojo/acl.py
sapiopylib/rest/pojo/session.py
sapiopylib/rest/pojo/chartdata/ChartData.py
sapiopylib/rest/pojo/chartdata/DashboardDefinition.py
sapiopylib/rest/pojo/chartdata/DashboardEnums.py
sapiopylib/rest/pojo/chartdata/DashboardSeries.py
sapiopylib/rest/pojo/chartdata/__init__.py
sapiopylib/rest/pojo/datatype/DataType.py
sapiopylib/rest/pojo/datatype/DataTypeComponent.py
sapiopylib/rest/pojo/datatype/DataTypeDescriptors.py
sapiopylib-2025.10.7.295.dist-info/METADATA
sapiopylib-2025.10.7.295.dist-info/WHEEL
sapiopylib-2025.10.7.295.dist-info/licenses/LICENSE
sapiopylib-2025.10.7.295.dist-info/RECORD
