Metadata-Version: 2.3
Name: sapiopylib
Version: 2025.10.7.295
Summary: Official Sapio Informatics Platform Python API
Project-URL: Homepage, https://github.com/sapiosciences
Project-URL: Bug Tracker, https://github.com/sapiosciences/sapio-py-tutorials/issues
Author-email: Yechen Qiao <yqiao@sapiosciences.com>
License: MPL-2.0
Keywords: eln,lims,rest,sapio
Classifier: Development Status :: 5 - Production/Stable
Classifier: Intended Audience :: Developers
Classifier: Intended Audience :: Healthcare Industry
Classifier: Intended Audience :: Science/Research
Classifier: License :: OSI Approved :: Mozilla Public License 2.0 (MPL 2.0)
Classifier: Operating System :: OS Independent
Classifier: Programming Language :: Python :: 3.10
Classifier: Topic :: Scientific/Engineering :: Bio-Informatics
Classifier: Topic :: Software Development :: Libraries :: Python Modules
Requires-Python: >=3.10
Requires-Dist: buslane>=0.0.5
Requires-Dist: flask>=2.2.0
Requires-Dist: kaleido<0.3.0,>=0.2.0
Requires-Dist: numpyencoder>=0.3.0
Requires-Dist: pandas>=1.3.0
Requires-Dist: plotly<6.0.0
Requires-Dist: plotly>=5.14.0
Requires-Dist: requests>=2.28.1
Requires-Dist: scipy>=1.11.1
